empire-erp/__init__.py
empire-erp/accounting/__init__.py
empire-erp/accounting/game.py
empire_erp/__init__.py
empire_erp/accounting/__init__.py
empire_erp/accounting/game.py
empire_erp-0.0.3.dist-info/LICENSE
empire_erp-0.0.3.dist-info/METADATA
empire_erp-0.0.3.dist-info/WHEEL
empire_erp-0.0.3.dist-info/top_level.txt
empire_erp-0.0.3.dist-info/RECORD
