Metadata-Version: 2.1
Name: empire-erp
Version: 0.0.3
Summary: Empire ERP
Home-page: https://github.com/nomhoi/empire-erp
Author: Vladimir Nomkhoev
Author-email: n_vova@mail.ru
License: UNKNOWN
Platform: UNKNOWN
Classifier: Programming Language :: Python :: 3
Classifier: License :: OSI Approved :: GNU General Public License v3 (GPLv3)
Classifier: Operating System :: OS Independent
